odoo/addons/sale_order_line_min_margin/README.rst
odoo/addons/sale_order_line_min_margin/__init__.py
odoo/addons/sale_order_line_min_margin/__manifest__.py
odoo/addons/sale_order_line_min_margin/i18n/es.po
odoo/addons/sale_order_line_min_margin/models/__init__.py
odoo/addons/sale_order_line_min_margin/models/res_company.py
odoo/addons/sale_order_line_min_margin/models/res_config_settings.py
odoo/addons/sale_order_line_min_margin/models/sale_order_line.py
odoo/addons/sale_order_line_min_margin/static/description/icon.png
odoo/addons/sale_order_line_min_margin/views/res_config_settings_views.xml
odoo_addon_sale_order_line_min_margin-15.0.1.0.1.dist-info/METADATA
odoo_addon_sale_order_line_min_margin-15.0.1.0.1.dist-info/WHEEL
odoo_addon_sale_order_line_min_margin-15.0.1.0.1.dist-info/top_level.txt
odoo_addon_sale_order_line_min_margin-15.0.1.0.1.dist-info/RECORD
