Metadata-Version: 2.1
Name: odoo-addon-sale_order_line_min_margin
Version: 15.0.1.0.1
Requires-Python: >=3.8
Requires-Dist: odoo>=15.0a,<15.1dev
Summary: Set minimum margin in sale order lines
Home-page: https://github.com/sygel-technology/sy-sale-workflow
License: AGPL-3
Author: Sygel
Classifier: Programming Language :: Python
Classifier: Framework :: Odoo
Classifier: Framework :: Odoo :: 15.0
Classifier: License :: OSI Approved :: GNU Affero General Public License v3
